CHANGES.txt
DESC.txt
LICENSE.txt
MANIFEST.in
README.md
requirements.txt
setup.py
Requirementz.egg-info/PKG-INFO
Requirementz.egg-info/SOURCES.txt
Requirementz.egg-info/dependency_links.txt
Requirementz.egg-info/entry_points.txt
Requirementz.egg-info/requires.txt
Requirementz.egg-info/top_level.txt
docs/README.rst
requirementz/__init__.py
requirementz/__main__.py
requirementz/tools.py
test/test_requirementz.py