Metadata-Version: 1.1
Name: Requirementz
Version: 0.3.5
Summary: Checks pip requirements against installed versions, and other related tools.
